{
  "openapi": "3.0.1",
  "info": {
    "title": "Minha API",
    "version": "v1"
  },
  "paths": {
    "/api/Area": {
      "get": {
        "tags": [
          "Area"
        ],
        "responses": {
          "200": {
            "description": "OK"
          }
        }
      },
      "post": {
        "tags": [
          "Area"
        ],
        "requestBody": {
          "content": {
            "application/json": {
              "schema": {
                "$ref": "#/components/schemas/AreaRequest"
              }
            },
            "text/json": {
              "schema": {
                "$ref": "#/components/schemas/AreaRequest"
              }
            },
            "application/*+json": {
              "schema": {
                "$ref": "#/components/schemas/AreaRequest"
              }
            }
          }
        },
        "responses": {
          "200": {
            "description": "OK"
          }
        }
      }
    },
    "/api/Area/id": {
      "get": {
        "tags": [
          "Area"
        ],
        "parameters": [
          {
            "name": "id",
            "in": "query",
            "schema": {
              "type": "integer",
              "format": "int32"
            }
          }
        ],
        "responses": {
          "200": {
            "description": "OK"
          }
        }
      }
    },
    "/api/Area/{id}": {
      "delete": {
        "tags": [
          "Area"
        ],
        "parameters": [
          {
            "name": "id",
            "in": "path",
            "required": true,
            "schema": {
              "type": "integer",
              "format": "int32"
            }
          }
        ],
        "responses": {
          "200": {
            "description": "OK"
          }
        }
      },
      "put": {
        "tags": [
          "Area"
        ],
        "parameters": [
          {
            "name": "id",
            "in": "path",
            "required": true,
            "schema": {
              "type": "integer",
              "format": "int32"
            }
          }
        ],
        "requestBody": {
          "content": {
            "application/json": {
              "schema": {
                "$ref": "#/components/schemas/AreaRequest"
              }
            },
            "text/json": {
              "schema": {
                "$ref": "#/components/schemas/AreaRequest"
              }
            },
            "application/*+json": {
              "schema": {
                "$ref": "#/components/schemas/AreaRequest"
              }
            }
          }
        },
        "responses": {
          "200": {
            "description": "OK"
          }
        }
      }
    },
    "/api/Auth/cadastro": {
      "post": {
        "tags": [
          "Auth"
        ],
        "requestBody": {
          "content": {
            "application/json": {
              "schema": {
                "$ref": "#/components/schemas/LoginCadastraRequest"
              }
            },
            "text/json": {
              "schema": {
                "$ref": "#/components/schemas/LoginCadastraRequest"
              }
            },
            "application/*+json": {
              "schema": {
                "$ref": "#/components/schemas/LoginCadastraRequest"
              }
            }
          }
        },
        "responses": {
          "200": {
            "description": "OK"
          }
        }
      }
    },
    "/api/Auth/me": {
      "get": {
        "tags": [
          "Auth"
        ],
        "responses": {
          "200": {
            "description": "OK"
          }
        }
      }
    },
    "/api/Auth/login": {
      "post": {
        "tags": [
          "Auth"
        ],
        "requestBody": {
          "content": {
            "application/json": {
              "schema": {
                "$ref": "#/components/schemas/LoginRequest"
              }
            },
            "text/json": {
              "schema": {
                "$ref": "#/components/schemas/LoginRequest"
              }
            },
            "application/*+json": {
              "schema": {
                "$ref": "#/components/schemas/LoginRequest"
              }
            }
          }
        },
        "responses": {
          "200": {
            "description": "OK"
          }
        }
      }
    },
    "/api/Auth/refresh": {
      "post": {
        "tags": [
          "Auth"
        ],
        "requestBody": {
          "content": {
            "application/json": {
              "schema": {
                "$ref": "#/components/schemas/TokenRefreshRequest"
              }
            },
            "text/json": {
              "schema": {
                "$ref": "#/components/schemas/TokenRefreshRequest"
              }
            },
            "application/*+json": {
              "schema": {
                "$ref": "#/components/schemas/TokenRefreshRequest"
              }
            }
          }
        },
        "responses": {
          "200": {
            "description": "OK"
          }
        }
      }
    },
    "/api/Programa": {
      "get": {
        "tags": [
          "Programa"
        ],
        "responses": {
          "200": {
            "description": "OK"
          }
        }
      },
      "post": {
        "tags": [
          "Programa"
        ],
        "requestBody": {
          "content": {
            "application/json": {
              "schema": {
                "$ref": "#/components/schemas/ProgramaResponse"
              }
            },
            "text/json": {
              "schema": {
                "$ref": "#/components/schemas/ProgramaResponse"
              }
            },
            "application/*+json": {
              "schema": {
                "$ref": "#/components/schemas/ProgramaResponse"
              }
            }
          }
        },
        "responses": {
          "200": {
            "description": "OK"
          }
        }
      }
    },
    "/api/Programa/{id}": {
      "get": {
        "tags": [
          "Programa"
        ],
        "parameters": [
          {
            "name": "id",
            "in": "path",
            "required": true,
            "schema": {
              "type": "integer",
              "format": "int32"
            }
          }
        ],
        "responses": {
          "200": {
            "description": "OK"
          }
        }
      },
      "put": {
        "tags": [
          "Programa"
        ],
        "parameters": [
          {
            "name": "id",
            "in": "path",
            "required": true,
            "schema": {
              "type": "integer",
              "format": "int32"
            }
          }
        ],
        "requestBody": {
          "content": {
            "application/json": {
              "schema": {
                "$ref": "#/components/schemas/ProgramaResponse"
              }
            },
            "text/json": {
              "schema": {
                "$ref": "#/components/schemas/ProgramaResponse"
              }
            },
            "application/*+json": {
              "schema": {
                "$ref": "#/components/schemas/ProgramaResponse"
              }
            }
          }
        },
        "responses": {
          "200": {
            "description": "OK"
          }
        }
      },
      "delete": {
        "tags": [
          "Programa"
        ],
        "parameters": [
          {
            "name": "id",
            "in": "path",
            "required": true,
            "schema": {
              "type": "integer",
              "format": "int32"
            }
          }
        ],
        "responses": {
          "200": {
            "description": "OK"
          }
        }
      }
    },
    "/api/SolicitacaoAcessoPrograma": {
      "get": {
        "tags": [
          "SolicitacaoAcessoPrograma"
        ],
        "responses": {
          "200": {
            "description": "OK"
          }
        }
      },
      "post": {
        "tags": [
          "SolicitacaoAcessoPrograma"
        ],
        "requestBody": {
          "content": {
            "application/json": {
              "schema": {
                "$ref": "#/components/schemas/SolicitacaoAcessoProgramaRequest"
              }
            },
            "text/json": {
              "schema": {
                "$ref": "#/components/schemas/SolicitacaoAcessoProgramaRequest"
              }
            },
            "application/*+json": {
              "schema": {
                "$ref": "#/components/schemas/SolicitacaoAcessoProgramaRequest"
              }
            }
          }
        },
        "responses": {
          "200": {
            "description": "OK"
          }
        }
      }
    },
    "/api/SolicitacaoAcessoPrograma/minhas-solicitacoes": {
      "get": {
        "tags": [
          "SolicitacaoAcessoPrograma"
        ],
        "responses": {
          "200": {
            "description": "OK"
          }
        }
      }
    },
    "/api/SolicitacaoAcessoPrograma/solicitacoes-pendentes-aprovacao": {
      "get": {
        "tags": [
          "SolicitacaoAcessoPrograma"
        ],
        "responses": {
          "200": {
            "description": "OK"
          }
        }
      }
    },
    "/api/SolicitacaoAcessoPrograma/{id}/decisao": {
      "put": {
        "tags": [
          "SolicitacaoAcessoPrograma"
        ],
        "parameters": [
          {
            "name": "id",
            "in": "path",
            "required": true,
            "schema": {
              "type": "integer",
              "format": "int32"
            }
          }
        ],
        "requestBody": {
          "content": {
            "application/json": {
              "schema": {
                "$ref": "#/components/schemas/DecisaoRequest"
              }
            },
            "text/json": {
              "schema": {
                "$ref": "#/components/schemas/DecisaoRequest"
              }
            },
            "application/*+json": {
              "schema": {
                "$ref": "#/components/schemas/DecisaoRequest"
              }
            }
          }
        },
        "responses": {
          "200": {
            "description": "OK"
          }
        }
      }
    },
    "/api/UsuarioWorkflow": {
      "get": {
        "tags": [
          "UsuarioWorkflow"
        ],
        "responses": {
          "200": {
            "description": "OK"
          }
        }
      },
      "post": {
        "tags": [
          "UsuarioWorkflow"
        ],
        "requestBody": {
          "content": {
            "application/json": {
              "schema": {
                "$ref": "#/components/schemas/UsuarioWorkflowRequest"
              }
            },
            "text/json": {
              "schema": {
                "$ref": "#/components/schemas/UsuarioWorkflowRequest"
              }
            },
            "application/*+json": {
              "schema": {
                "$ref": "#/components/schemas/UsuarioWorkflowRequest"
              }
            }
          }
        },
        "responses": {
          "200": {
            "description": "OK"
          }
        }
      }
    },
    "/api/UsuarioWorkflow/id": {
      "get": {
        "tags": [
          "UsuarioWorkflow"
        ],
        "parameters": [
          {
            "name": "id",
            "in": "query",
            "schema": {
              "type": "integer",
              "format": "int32"
            }
          }
        ],
        "responses": {
          "200": {
            "description": "OK"
          }
        }
      }
    },
    "/api/UsuarioWorkflow/{id}": {
      "put": {
        "tags": [
          "UsuarioWorkflow"
        ],
        "parameters": [
          {
            "name": "id",
            "in": "path",
            "required": true,
            "schema": {
              "type": "integer",
              "format": "int32"
            }
          }
        ],
        "requestBody": {
          "content": {
            "application/json": {
              "schema": {
                "$ref": "#/components/schemas/UsuarioWorkflowRequest"
              }
            },
            "text/json": {
              "schema": {
                "$ref": "#/components/schemas/UsuarioWorkflowRequest"
              }
            },
            "application/*+json": {
              "schema": {
                "$ref": "#/components/schemas/UsuarioWorkflowRequest"
              }
            }
          }
        },
        "responses": {
          "200": {
            "description": "OK"
          }
        }
      },
      "delete": {
        "tags": [
          "UsuarioWorkflow"
        ],
        "parameters": [
          {
            "name": "id",
            "in": "path",
            "required": true,
            "schema": {
              "type": "integer",
              "format": "int32"
            }
          }
        ],
        "responses": {
          "200": {
            "description": "OK"
          }
        }
      }
    }
  },
  "components": {
    "schemas": {
      "AreaRequest": {
        "type": "object",
        "properties": {
          "nome": {
            "type": "string",
            "nullable": true
          },
          "descricao": {
            "type": "string",
            "nullable": true
          },
          "responsavelAreaId": {
            "type": "integer",
            "format": "int32",
            "nullable": true
          }
        },
        "additionalProperties": false
      },
      "DecisaoRequest": {
        "type": "object",
        "properties": {
          "tipo": {
            "$ref": "#/components/schemas/TipoDecisao"
          },
          "aprovado": {
            "type": "boolean"
          }
        },
        "additionalProperties": false
      },
      "LoginCadastraRequest": {
        "type": "object",
        "properties": {
          "username": {
            "type": "string",
            "nullable": true
          },
          "usuarioWorkflowId": {
            "type": "integer",
            "format": "int32"
          },
          "password": {
            "type": "string",
            "nullable": true
          }
        },
        "additionalProperties": false
      },
      "LoginRequest": {
        "type": "object",
        "properties": {
          "username": {
            "type": "string",
            "nullable": true
          },
          "password": {
            "type": "string",
            "nullable": true
          }
        },
        "additionalProperties": false
      },
      "PerfilEnum": {
        "enum": [
          1,
          2,
          3
        ],
        "type": "integer",
        "format": "int32"
      },
      "ProgramaResponse": {
        "type": "object",
        "properties": {
          "id": {
            "type": "integer",
            "format": "int32"
          },
          "nome": {
            "type": "string",
            "nullable": true
          },
          "areaId": {
            "type": "integer",
            "format": "int32"
          }
        },
        "additionalProperties": false
      },
      "SolicitacaoAcessoProgramaRequest": {
        "type": "object",
        "properties": {
          "usuarioWorkflowId": {
            "type": "integer",
            "format": "int32"
          },
          "programaId": {
            "type": "integer",
            "format": "int32"
          }
        },
        "additionalProperties": false
      },
      "TipoDecisao": {
        "enum": [
          1,
          2,
          3
        ],
        "type": "integer",
        "format": "int32"
      },
      "TokenRefreshRequest": {
        "type": "object",
        "properties": {
          "refreshToken": {
            "type": "string",
            "nullable": true
          }
        },
        "additionalProperties": false
      },
      "UsuarioWorkflowRequest": {
        "type": "object",
        "properties": {
          "nome": {
            "type": "string",
            "nullable": true
          },
          "areaId": {
            "type": "integer",
            "format": "int32"
          },
          "perfil": {
            "$ref": "#/components/schemas/PerfilEnum"
          }
        },
        "additionalProperties": false
      }
    },
    "securitySchemes": {
      "Bearer": {
        "type": "http",
        "description": "Digite 'Bearer {seu token}' no campo abaixo.",
        "scheme": "Bearer",
        "bearerFormat": "JWT"
      }
    }
  },
  "security": [
    {
      "Bearer": [ ]
    }
  ]
}